pyokaka/__init__.py
pyokaka/transtable.json
pyokaka/okaka/__init__.py
pyokaka/okaka/__main__.py
pyokaka/okaka/convert.py
pyokaka/util/__init__.py
pyokaka/util/priority_dict.py
pyokaka-1.0.0.dist-info/LICENSE
pyokaka-1.0.0.dist-info/METADATA
pyokaka-1.0.0.dist-info/WHEEL
pyokaka-1.0.0.dist-info/top_level.txt
pyokaka-1.0.0.dist-info/RECORD
