Metadata-Version: 2.1
Name: pyokaka
Version: 1.0.0
Summary: Simple tool to translate from Roma-ji into Hiragana.
Home-page: https://github.com/LouiS0616/pyokaka
Author: LouiSakaki
Author-email: e1352207@outlook.jp
License: MIT
Platform: UNKNOWN
Requires-Python: >=3.6
